agent_framework_mlx/__init__.py
agent_framework_mlx/client.py
agent_framework_mlx-0.4.1.dist-info/METADATA
agent_framework_mlx-0.4.1.dist-info/WHEEL
agent_framework_mlx-0.4.1.dist-info/licenses/LICENSE
agent_framework_mlx-0.4.1.dist-info/RECORD
