Metadata-Version: 2.4
Name: agent-framework-mlx
Version: 0.4.1
Summary: MLX integration for the Agent Framework
Project-URL: Homepage, https://github.com/filipw/agent-framework-mlx
Author-email: Filip W <contact@strathweb.com>
License-Expression: MIT
License-File: LICENSE
Classifier: License :: OSI Approved :: MIT License
Classifier: Operating System :: MacOS :: MacOS X
Classifier: Programming Language :: Python :: 3
Requires-Python: >=3.9
Requires-Dist: agent-framework-core==1.0.0b260123
Requires-Dist: mlx-lm>=0.28.3
Requires-Dist: pydantic>=2.0.0
Provides-Extra: test
Requires-Dist: pytest; extra == 'test'
Requires-Dist: pytest-asyncio; extra == 'test'
